concept_extractor/__init__.py
concept_extractor/main.py
concept_extractor/prompts.py
concept_extractor-2025.12.21170754.dist-info/METADATA
concept_extractor-2025.12.21170754.dist-info/WHEEL
concept_extractor-2025.12.21170754.dist-info/top_level.txt
concept_extractor-2025.12.21170754.dist-info/RECORD
