Metadata-Version: 2.4
Name: concept-extractor
Version: 2025.12.21170754
Summary: A new package is designed to process complex conceptual prompts like 'Dark Enlightenment' by leveraging language models with structured pattern matching. Users provide a descriptive text input related
Author-email: concept-extractor <hi@eugene.plus>
License: MIT
Project-URL: Homepage, https://github.com/chigwell/concept-extractor
Requires-Python: >=3.9
Requires-Dist: langchain-llm7>=0.0.0
Requires-Dist: llmatch-messages>=0.0.0
Requires-Dist: langchain-core>=0.3.0
